{"tweets":[{"id":"1614283050900426753","text":"I am building a thing right now with some friends, I'm not sure exactly what it is, let alone a name for it, but in order for me to gather tools around it, I am constantly bombarded by requests for names- what to name the folder? the GH repo? the discord channel?","year":2023,"date":"2023-01-14","favorites":2,"retweets":0,"replyTo":"mrejfox"},{"id":"1614282791029706753","text":"computers almost always ask you to name things at the time of creation- that is not how names are given, names are usually given after a period of assessment and discussion, at the end of the process, such that the name captures the essence of the thing","year":2023,"date":"2023-01-14","favorites":5,"retweets":1,"replyTo":null},{"id":"1614275719483502593","text":"RT @StefGotBooted: Hear me out: Nuremberg Trials but for oil executives. https://t.co/6hT9ui2MOG","year":2023,"date":"2023-01-14","favorites":0,"retweets":0,"replyTo":null},{"id":"1481790947121848321","text":"visual proof of my ability to blend into a corporate environment (2018) https://t.co/BQPTTNNUiK","year":2022,"date":"2022-01-14","favorites":2,"retweets":0,"replyTo":null},{"id":"1349782202402435072","text":"@swodinsky Consent!!!","year":2021,"date":"2021-01-14","favorites":1,"retweets":0,"replyTo":"swodinsky"},{"id":"1349735762078666752","text":"https://t.co/gk43TV75ip","year":2021,"date":"2021-01-14","favorites":2,"retweets":0,"replyTo":"mrejfox"},{"id":"1349598204128600064","text":"RT @GuardianUS: US police three times as likely to use force against leftwing protesters, data finds https://t.co/livkGZgIuX","year":2021,"date":"2021-01-14","favorites":0,"retweets":0,"replyTo":null},{"id":"1349593013048250368","text":"what the fuck https://t.co/26dw17vCCO","year":2021,"date":"2021-01-14","favorites":2,"retweets":0,"replyTo":null},{"id":"1349549330806538241","text":"@oneunderscore__ this is weird because every time I see you I also say \"savvy, sexy, mystery-ly\" in my internal monologue","year":2021,"date":"2021-01-14","favorites":2,"retweets":0,"replyTo":"oneunderscore__"},{"id":"1084907171454873601","text":"Death throes of our society’s brief affair with putting black box algorithms in charge of our friendships and self expression https://t.co/Cd6XgvHftS","year":2019,"date":"2019-01-14","favorites":0,"retweets":0,"replyTo":null},{"id":"1084901973168742403","text":"RT @claytoncubitt: Annual cost of property crime (robberies, burglaries, etc): $12.7b\n\nAnnual cost of wage theft by employers: $15b\n\nhttps:…","year":2019,"date":"2019-01-14","favorites":0,"retweets":0,"replyTo":null},{"id":"1084893810310688769","text":"@JesseKellyDC Jesse you know we can all see this right","year":2019,"date":"2019-01-14","favorites":9,"retweets":0,"replyTo":"JesseKellyDC"},{"id":"1084889799612346369","text":"@mattdunnam Yeah exactly","year":2019,"date":"2019-01-14","favorites":0,"retweets":0,"replyTo":"mattdunnam"},{"id":"1084884250023866370","text":"@mattdunnam I think trying to make CMSes that try to scale is part of the problem - CMS monoculture breeds content monoculture. Open source software has the same problem. Instagram Stories is the best user facing CMS we have in 2019 imo.","year":2019,"date":"2019-01-14","favorites":0,"retweets":0,"replyTo":"mattdunnam"},{"id":"1084845338253553664","text":"Dispatch from New Jersey https://t.co/kZUsDwZ9ti","year":2019,"date":"2019-01-14","favorites":0,"retweets":0,"replyTo":null},{"id":"1084840568612667392","text":"This is a viable solution for large companies with profit margin at stakes. What about a new CMS for personal expression and human networking? We need to build it ourselves. https://t.co/xHeMoJ6Frs","year":2019,"date":"2019-01-14","favorites":0,"retweets":0,"replyTo":null},{"id":"1084838607033118720","text":"The general atmosphere and clientele of the local radiology departments do not take kindly to when I roll cigarettes in the waiting room","year":2019,"date":"2019-01-14","favorites":1,"retweets":0,"replyTo":null},{"id":"952642950504345600","text":"@mdavidallen very wise","year":2018,"date":"2018-01-14","favorites":0,"retweets":0,"replyTo":"mdavidallen"},{"id":"952641999072628736","text":"If you only take the congressional districts Hillary won in 2016 and flip them blue the GOP only has one district to spare (a big if, obviously) https://t.co/zB6RCnLmyP","year":2018,"date":"2018-01-14","favorites":0,"retweets":0,"replyTo":null},{"id":"952620952969449472","text":"Why do you guys think I am so consistently attracted people with an inability to commit to anything (do you think it is my own inability to commit to anything?)","year":2018,"date":"2018-01-14","favorites":1,"retweets":0,"replyTo":null},{"id":"952596503746547718","text":"Got really annoyed at a person not respecting my personal space and acting generally entitled in the coffee shop and then was later informed they are a Famed Television Personality","year":2018,"date":"2018-01-14","favorites":0,"retweets":0,"replyTo":null},{"id":"952588014076743681","text":"When you consider being up to date on the news being on a scale from 1-5, 1 being knowing nearly nothing, and 5 is staying up to date on every minute controversy, have found shifting from a 5 to a 3-4 increases mental health by magnitude but I don’t really miss anything","year":2018,"date":"2018-01-14","favorites":0,"retweets":0,"replyTo":null},{"id":"952567337890271238","text":"It is hard for me to not fall in love with girls who grab my cigarettes and take a drag without asking.","year":2018,"date":"2018-01-14","favorites":1,"retweets":0,"replyTo":null},{"id":"952565533702008832","text":"RT @brosandprose: We need to stop dividing men into \"nice guys\" and \"jerks.\" That Venn Diagram is a circle. There are only men who have fuc…","year":2018,"date":"2018-01-14","favorites":0,"retweets":0,"replyTo":null},{"id":"952558612400001024","text":"We cover pendulum swings like a horse race","year":2018,"date":"2018-01-14","favorites":0,"retweets":0,"replyTo":null},{"id":"820318113896026116","text":"RT @michaelmalice: Trump's attacks on John Lewis are precisely what his base lives for: the evisceration of progressive taboos.","year":2017,"date":"2017-01-14","favorites":0,"retweets":0,"replyTo":null},{"id":"820317751646584833","text":"I grow weary","year":2017,"date":"2017-01-14","favorites":0,"retweets":0,"replyTo":null},{"id":"820301187849261056","text":"Looking for more folks who use @gyroscope_app! Add me as a friend (username ejfox) https://t.co/ONGsIMoFLd","year":2017,"date":"2017-01-14","favorites":0,"retweets":0,"replyTo":null},{"id":"820296492061696000","text":"Our next John Lewis is currently organizing to March on Washington on Jan 20/21. Our next John Lewis was teargassed in Baltimore &amp; Ferguson.","year":2017,"date":"2017-01-14","favorites":2,"retweets":1,"replyTo":null},{"id":"820292165528121344","text":"RT @repjohnlewis: Marching along the highway from Selma to Montgomery, we were met by hatred and intimidation. We did not turn back. https:…","year":2017,"date":"2017-01-14","favorites":0,"retweets":0,"replyTo":null},{"id":"820290256545189888","text":"@TravelingAnna and we will be here again. I will use the tools my elders in the 60s etc. made for me, and make new tools as well.","year":2017,"date":"2017-01-14","favorites":0,"retweets":0,"replyTo":"TravelingAnna"},{"id":"820287411477430272","text":"@TravelingAnna very much disagree. Issues ignored by large parts of establishment are at forefront now. Apathy is not an option. Good.","year":2017,"date":"2017-01-14","favorites":0,"retweets":0,"replyTo":"TravelingAnna"},{"id":"687765904743071744","text":"@MeltingIce You using the Hue? I feel like they blink for too long...","year":2016,"date":"2016-01-14","favorites":0,"retweets":0,"replyTo":"MeltingIce"},{"id":"687734495861190656","text":"all I wanna do is blast rap music in the office as loud as my speakers go","year":2016,"date":"2016-01-14","favorites":0,"retweets":0,"replyTo":null},{"id":"687718126776102913","text":"Today, like many other days, @bylukemalone is a god among men.","year":2016,"date":"2016-01-14","favorites":2,"retweets":0,"replyTo":null},{"id":"687712035782692865","text":"Combine ALL the memes! \n\nhttps://t.co/AA06RygYVx","year":2016,"date":"2016-01-14","favorites":0,"retweets":0,"replyTo":null},{"id":"687672796063907841","text":"RT @shirleyxywu: I appreciate the analogies loads, @enjalot, thank you :D.  #dataviz is like any other craft; it takes time and care https:…","year":2016,"date":"2016-01-14","favorites":0,"retweets":0,"replyTo":null},{"id":"687643768619712512","text":"RT @mkramer: Yo journalists: make sure you have PDFs of all of your work before the place you’re writing for disappears \n\nhttps://t.co/iL9C…","year":2016,"date":"2016-01-14","favorites":0,"retweets":0,"replyTo":null},{"id":"687643195476426752","text":"RT @JebBush: Thanks @djkhaled — had my green apples for breakfast https://t.co/aPiA7askZ8","year":2016,"date":"2016-01-14","favorites":0,"retweets":0,"replyTo":null},{"id":"687642444838637568","text":"@carolinelinton legit hippie is my new band name","year":2016,"date":"2016-01-14","favorites":1,"retweets":0,"replyTo":"carolinelinton"},{"id":"687431942665547777","text":"Listen, there’s annuity people, and there are lump sum people.","year":2016,"date":"2016-01-14","favorites":0,"retweets":0,"replyTo":null},{"id":"555492791355457536","text":"The Economist has weird rolex-sponsored save-for-later feature that I’ve not seen before: http://t.co/mW3tbk8X19","year":2015,"date":"2015-01-14","favorites":0,"retweets":0,"replyTo":null},{"id":"555165108859850752","text":"RT @taylor_owen: this RT @knightfdn: \"It's a tough time to be a 52 yr old journalist, but it's a great time to be a 22 yr old journalist.\" …","year":2015,"date":"2015-01-14","favorites":0,"retweets":0,"replyTo":null},{"id":"423236349911498752","text":"@FreeJeremyNet How can I add directly to his commissary, no intermediary?","year":2014,"date":"2014-01-14","favorites":0,"retweets":0,"replyTo":"FreeJeremyNet"},{"id":"423184784492199936","text":"@ptvan I have a haircut at 2 (for free!) and will come straight after!","year":2014,"date":"2014-01-14","favorites":0,"retweets":0,"replyTo":"ptvan"},{"id":"423163190118055936","text":"RT @rendesr: Wrote a MONSTER guide on Anchor CMS - you can read it here: http://t.co/OKqT6FsRsh @anchorcms #texfly","year":2014,"date":"2014-01-14","favorites":0,"retweets":0,"replyTo":null},{"id":"423152018673242112","text":"@poezn No worries! I’m here Jan 27-31 if I miss you guys today, too.","year":2014,"date":"2014-01-14","favorites":0,"retweets":0,"replyTo":"poezn"},{"id":"423148864816697344","text":"@ptvan @poezn Whens a good time after 2:30 that I could swing by @hlftn (if thats still cool)?","year":2014,"date":"2014-01-14","favorites":0,"retweets":0,"replyTo":"ptvan"},{"id":"290950222094405632","text":"Unlike this year, I think I feel like actually celebrating my next birthday. Just in time, too, that's the 21 one.","year":2013,"date":"2013-01-14","favorites":0,"retweets":0,"replyTo":null},{"id":"290949249582133251","text":"RT @roginkim: Applying for jobs online is a lot like tossing coins into a wishing well, except that it takes way longer.","year":2013,"date":"2013-01-14","favorites":0,"retweets":0,"replyTo":null},{"id":"290947086021709824","text":"RT @mibi: Sometimes the single most productive thing you can do is #sleep.","year":2013,"date":"2013-01-14","favorites":0,"retweets":0,"replyTo":null},{"id":"290932330284064769","text":"Up and out of bed. 4:36PM.","year":2013,"date":"2013-01-14","favorites":0,"retweets":0,"replyTo":null},{"id":"290931771204304897","text":"@marcfawzi Cheers, thanks! Your enthusiasm makes this work go much quicker on my end, funny how that is...","year":2013,"date":"2013-01-14","favorites":0,"retweets":0,"replyTo":null},{"id":"290678714797281280","text":"Spent today working on a new look for Tributary http://t.co/o1p7H2aF","year":2013,"date":"2013-01-14","favorites":0,"retweets":0,"replyTo":null},{"id":"158225421995999232","text":"RT @zuchinno: @OccupyOOTAC @Occupythemob @LadyGoftheTAC OPD already wants to beat & snatch us. If ppl wanna be militant, do so for our p ...","year":2012,"date":"2012-01-14","favorites":0,"retweets":0,"replyTo":null},{"id":"158045616306536448","text":"RT @socialistlib510: Where are Quan's emails? #occupyoakland","year":2012,"date":"2012-01-14","favorites":0,"retweets":0,"replyTo":null},{"id":"158044831866822656","text":"RT @socialistlib510: OPD + City Colluding 2 Destroy Political Mvmnt now proven. Facts should be used against bth. Proves targeting at OG ...","year":2012,"date":"2012-01-14","favorites":0,"retweets":0,"replyTo":null},{"id":"158044568036712448","text":"RT @saltcityhoops: Instagram should buy troubled Polaroid and make Bluetooth printers for the iPhone. Instant digital hipster photo prin ...","year":2012,"date":"2012-01-14","favorites":0,"retweets":0,"replyTo":null},{"id":"7763028324","text":"Shit. My Flickr is in french.","year":2010,"date":"2010-01-14","favorites":0,"retweets":0,"replyTo":null},{"id":"7758214932","text":"Sleep is not sacred. Sleep ain't no ritual.","year":2010,"date":"2010-01-14","favorites":0,"retweets":0,"replyTo":null},{"id":"7752738901","text":"Shallow depth of field pictures & movies of mixing boards is one of those things that \"does it for me\".","year":2010,"date":"2010-01-14","favorites":0,"retweets":0,"replyTo":null},{"id":"7748538129","text":"Shared: The Two Gentlemen of Lebowski, live in NYC: Working quickly, the DMTheatrics theater company has.. http://bit.ly/57XeLY","year":2010,"date":"2010-01-14","favorites":0,"retweets":0,"replyTo":null},{"id":"7746222324","text":"@lenasaur Hahaha, what a good employee! Have a good extra sleep!","year":2010,"date":"2010-01-14","favorites":0,"retweets":0,"replyTo":"leoF0x"},{"id":"7736628874","text":"Working and working and working and working.","year":2010,"date":"2010-01-14","favorites":0,"retweets":0,"replyTo":null},{"id":"1119517949","text":"I could easily cook food in a kitchen while listening to Tokyo Police Club & Born Ruffians for the rest of my life, I think.","year":2009,"date":"2009-01-14","favorites":0,"retweets":0,"replyTo":null},{"id":"1119285489","text":"Took a little nap. Then took a shower. New Axe shampoo is nice. I'm a cliche.","year":2009,"date":"2009-01-14","favorites":0,"retweets":0,"replyTo":null},{"id":"1119034002","text":"@chaosman I think that we should use SongSmith exclusively from now on: http://is.gd/fJrK","year":2009,"date":"2009-01-14","favorites":0,"retweets":0,"replyTo":"chaosman"},{"id":"1118988194","text":"I am in love with this girl: http://is.gd/fMhl","year":2009,"date":"2009-01-14","favorites":0,"retweets":0,"replyTo":null},{"id":"1118977843","text":"THERE'S GOTTA BE SOME WAY I CAN GET TO THE INAUGURATION","year":2009,"date":"2009-01-14","favorites":0,"retweets":0,"replyTo":null},{"id":"1118749459","text":"Trying to remember what breakup songs I love so I can force a breakup mix upon Taylyn. First: Roll On w/ Jenny Lewis by Dntel. Brilliant.","year":2009,"date":"2009-01-14","favorites":0,"retweets":0,"replyTo":null},{"id":"1118734995","text":"I'll hide my smile behind my hand, pretend everything's not so bad.","year":2009,"date":"2009-01-14","favorites":0,"retweets":0,"replyTo":null},{"id":"1118681323","text":"Dear Hulu, please don't add shows I've already watched to my queue and then email me about it. I get excited.","year":2009,"date":"2009-01-14","favorites":0,"retweets":0,"replyTo":null},{"id":"1118404623","text":"That was a great movie. Wonderful storytelling.","year":2009,"date":"2009-01-14","favorites":0,"retweets":0,"replyTo":null},{"id":"1118293439","text":"Is this metaphor or coincidence?","year":2009,"date":"2009-01-14","favorites":0,"retweets":0,"replyTo":null},{"id":"1118214690","text":"Gonna watch Burn After Reading as I finish my breakfast.","year":2009,"date":"2009-01-14","favorites":0,"retweets":0,"replyTo":null},{"id":"1118210846","text":"Proof that genius comes in all forms: http://is.gd/fQl1","year":2009,"date":"2009-01-14","favorites":0,"retweets":0,"replyTo":null},{"id":"1118189929","text":"http://twitpic.com/12qcy - Breakfast: grapefruit & honey, banana chips, a lil chili chocolate, and green-mint tea.","year":2009,"date":"2009-01-14","favorites":0,"retweets":0,"replyTo":null},{"id":"1118127763","text":"Awake & recording.","year":2009,"date":"2009-01-14","favorites":0,"retweets":0,"replyTo":null},{"id":"1117568831","text":"Wave of tiredness.. Gonna try and sleep.","year":2009,"date":"2009-01-14","favorites":0,"retweets":0,"replyTo":null},{"id":"1117399680","text":"I want to see Animal Collective at Central Park's Summerstage...","year":2009,"date":"2009-01-14","favorites":0,"retweets":0,"replyTo":null},{"id":"1117146754","text":"Chile Dark Chocolate is truly delicious. Can't wait for dinner tomorrow.","year":2009,"date":"2009-01-14","favorites":0,"retweets":0,"replyTo":null},{"id":"599129982","text":"Tumblr: Some pretty incredible fractal art&#8230; via BoingBoing http://tinyurl.com/yqryok","year":2008,"date":"2008-01-14","favorites":0,"retweets":0,"replyTo":null},{"id":"598946522","text":"Tumblr: An ad for Pakistan Airlines&#8230;. http://tinyurl.com/36zuxa","year":2008,"date":"2008-01-14","favorites":0,"retweets":0,"replyTo":null},{"id":"598946482","text":"Tumblr: I want one, so I can say &#8220;Want some eggs over-uzi?&#8221;... http://tinyurl.com/3a3khe","year":2008,"date":"2008-01-14","favorites":0,"retweets":0,"replyTo":null},{"id":"598847322","text":"Pi time.","year":2008,"date":"2008-01-14","favorites":0,"retweets":0,"replyTo":null},{"id":"598437552","text":"Playing with InDesign.","year":2008,"date":"2008-01-14","favorites":0,"retweets":0,"replyTo":null},{"id":"597696632","text":"Good morning, snow. I feel truly horrible. Thanks for the two hour delay- but I'm taking today off anyway.","year":2008,"date":"2008-01-14","favorites":0,"retweets":0,"replyTo":null},{"id":"595725892","text":"I feel like shit. My room's a mess. I have a bunch of homework to do. Midterms starting friday. ugh. ugh times a million.","year":2008,"date":"2008-01-14","favorites":0,"retweets":0,"replyTo":null},{"id":"595630882","text":"Tumblr: A picture of Arlen (My little brother) I took. I think it came... http://tinyurl.com/yucmjf","year":2008,"date":"2008-01-14","favorites":0,"retweets":0,"replyTo":null}],"posts":[{"slug":"drafts/_stale/personal-automation-patterns","title":"I Love n8n","year":2025,"date":"2025-01-14T15:20:05.000Z","dek":"In which","type":"post","tags":["example","design","inspiration"]}],"scrobbles":[{"date":"2024-01-14","year":2024,"count":6,"topTracks":["Sam Gellaitry - long distance","JayBucks - OPPS IS BUMS","NOCHILL - Edd","Glizzy07 - Glizzy (Mouvement de sabre)","JayBucks - SHE GOT OPPS 2"],"topArtists":["Sam Gellaitry","JayBucks","NOCHILL"]},{"date":"2023-01-14","year":2023,"count":40,"topTracks":["G4 Boyz - Birkin","JoeyAK - Blijf Soldaat","JayBucks - OPPS IS BUMS","Kay Flock - Is Ya Ready","Kenzo Balla - Evil Twins"],"topArtists":["G4 Boyz","JoeyAK","JayBucks"]},{"date":"2022-01-14","year":2022,"count":24,"topTracks":["Kay Flock - Opp Spotter (feat. B-Lovee)","Bizzy Banks - Neo","Stormzy - Wiley Flow","OSC & Vinja featuring The Spit Brothers - Originate","Antiserum - No Cap"],"topArtists":["Kay Flock","Bizzy Banks","Stormzy"]},{"date":"2021-01-14","year":2021,"count":62,"topTracks":["MUNA - Number One Fan","Smino - Baguetti (with JID & Kenny Beats)","Smino - Z4L (with Bari & Jay2)","Smino - Silk Pillows","Smino - Ricky Millions"],"topArtists":["MUNA","Smino","monte booker"]},{"date":"2016-01-14","year":2016,"count":9,"topTracks":["Young Thug - Best Friends","Young Thug - Constantly Hating - Original","Young Thug - Constantly Hating (feat. Birdman)","Young Thug - Never Had It (feat. Young Dolph)","Post Malone - White Iverson"],"topArtists":["Young Thug","Post Malone","A$AP Rocky"]},{"date":"2013-01-14","year":2013,"count":16,"topTracks":["Michael Franti - Ganja Babe","Chief Keef - Hallelujah","Chief Keef - I Don't Like","Khia - My Neck, My Back","Master P - Break 'Em Off Somethin'"],"topArtists":["Michael Franti","Chief Keef","Khia"]},{"date":"2011-01-14","year":2011,"count":33,"topTracks":["Simian Mobile Disco - The Beat (Siriusmo Mix)","Orson Scott Card - Speaker for the Dead (Unabridged), Part 1","Neal Stephenson - Snow Crash Unabridged, Part 1","Orson Scott Card - Children of the Mind (Unabridged), Part 1","James Carter and The Prisoners - Po' Lazarus"],"topArtists":["Simian Mobile Disco","Orson Scott Card","Neal Stephenson"]},{"date":"2009-01-14","year":2009,"count":112,"topTracks":["Jon Stewart and The Writers of <I>The Daily Show</I> - America (The Audiobook)","Animal Collective - My Girls","Animal Collective - In the Flowers","Animal Collective - Also Frightened","Animal Collective - Summertime Clothes"],"topArtists":["Jon Stewart and The Writers of <I>The Daily Show</I>","Animal Collective","Snoop Dogg"]},{"date":"2007-01-14","year":2007,"count":41,"topTracks":["Weekend America for January 13, 2007 - Hour 1: War and the Hajj....","Weekend America for January 13, 2007 - Hour 2: MLK and Change...","George Carlin - When Will Jesus Bring the Pork Chops? (Unabridged)","The Postal Service - Clark Gable","Sigur Rós - Njosnavelin (Nothing Song)"],"topArtists":["Weekend America for January 13, 2007","George Carlin","The Postal Service"]}],"commits":[]}