{"tweets":[{"id":"1588854746391384064","text":"RT @betterthemask: if you hate watching a billionaire destroy the place you live online, wait till you hear what they’re up to with planet…","year":2022,"date":"2022-11-05","favorites":0,"retweets":0,"replyTo":null},{"id":"1456641354684112901","text":"Continued long after I left school as well… https://t.co/h1QuBSseIo","year":2021,"date":"2021-11-05","favorites":0,"retweets":0,"replyTo":"mrejfox"},{"id":"1456640853649264642","text":"I was told racist jokes by fellow students in elementary school in upstate NY… so… probably before then https://t.co/k2rI9tlv2l","year":2021,"date":"2021-11-05","favorites":2,"retweets":0,"replyTo":null},{"id":"1456416231490297860","text":"@Caged This isn't answering your question at all but the most fun/flow I have had lately that rivals playing with the OP-1 is https://t.co/LTqRD8k9HD","year":2021,"date":"2021-11-05","favorites":2,"retweets":0,"replyTo":"Caged"},{"id":"1456412463461720070","text":"@Caged SP-404*","year":2021,"date":"2021-11-05","favorites":0,"retweets":0,"replyTo":"mrejfox"},{"id":"1456412274919415815","text":"@Caged I've been eagerly eyeing the Maschine Studio+ - the new SP-444 looks great too- the OP-1 is unparalleled for flow/fun though, imo. Mine has some dead keys so I am waiting for global logistics to allow me to purchase replacement keys. :(","year":2021,"date":"2021-11-05","favorites":0,"retweets":0,"replyTo":"Caged"},{"id":"1324376779080028160","text":"@scotthmurray Spicy tahini for the fries, its damn good, but I was too distracted to integrate it","year":2020,"date":"2020-11-05","favorites":0,"retweets":0,"replyTo":null},{"id":"1191739121322070016","text":"@Mantia the sharp jabby corners could hurt the children","year":2019,"date":"2019-11-05","favorites":1,"retweets":0,"replyTo":"Mantia"},{"id":"1191738891637788672","text":"I refuse to listen to, nor will I ever forgive, anyone referring to podcasts as \"pods\"","year":2019,"date":"2019-11-05","favorites":1,"retweets":0,"replyTo":null},{"id":"1191730052901359622","text":"every new poll should be accompanied with a footnote with how they predicted the 2016 general election","year":2019,"date":"2019-11-05","favorites":2,"retweets":0,"replyTo":null},{"id":"1191710459113684992","text":"@micahstubbs I dont disagree, but also I was imagining the thing baristas do when they squish an espresso shot https://t.co/uaROhjad0V","year":2019,"date":"2019-11-05","favorites":0,"retweets":0,"replyTo":"micahstubbs"},{"id":"1191545593795137536","text":"I earnestly wonder how much internet toxicity could be tampered by a “fuck you” button","year":2019,"date":"2019-11-05","favorites":4,"retweets":1,"replyTo":null},{"id":"1191528068734767105","text":"@geoffreyvs @WapoEngineering cc @SteveKornacki","year":2019,"date":"2019-11-05","favorites":0,"retweets":0,"replyTo":"geoffreyvs"},{"id":"1059581594502135808","text":"RT @Redistrict: Here's a peek at what we'll be up to at the @NBCNews Decision Desk tomorrow night: https://t.co/bpQXH99zYN","year":2018,"date":"2018-11-05","favorites":0,"retweets":0,"replyTo":null},{"id":"1059577926067388418","text":"RT @johnwilsonmsnbc: The Big Board on the big screen at 30 Rock featuring the one and only @SteveKornacki #MSNBC #2018Midterms https://t.co…","year":2018,"date":"2018-11-05","favorites":0,"retweets":0,"replyTo":null},{"id":"1059556737534095360","text":"RT @annthurium: \"JavaScript is the most popular language in the world right now...50% of working programmers use JS at least some of the ti…","year":2018,"date":"2018-11-05","favorites":0,"retweets":0,"replyTo":null},{"id":"1059544783360851968","text":"CAFFEINE","year":2018,"date":"2018-11-05","favorites":1,"retweets":0,"replyTo":null},{"id":"1059495356998844416","text":"https://t.co/heLFSsqjfb","year":2018,"date":"2018-11-05","favorites":1,"retweets":0,"replyTo":null},{"id":"1059439081225105408","text":"2019: \"pop-up\" news organizations","year":2018,"date":"2018-11-05","favorites":4,"retweets":0,"replyTo":null},{"id":"1059434542279331840","text":"RT @NYTmag: We're publishing next week's cover story early: \n\nU.S. law enforcement failed to see the threat of white nationalism. From the…","year":2018,"date":"2018-11-05","favorites":0,"retweets":0,"replyTo":null},{"id":"795005888813793281","text":"RT @bombblackgirlss: Alicia Keys for The Edit Magazine https://t.co/faqGObbsGQ","year":2016,"date":"2016-11-05","favorites":0,"retweets":0,"replyTo":null},{"id":"795005755862695936","text":"RT @deray: The #MannequinChallenge is dope. https://t.co/TQQBquUNDb","year":2016,"date":"2016-11-05","favorites":0,"retweets":0,"replyTo":null},{"id":"795004900862263300","text":"What. The. Fuck. \n\nhttps://t.co/zydDqudWCW","year":2016,"date":"2016-11-05","favorites":0,"retweets":0,"replyTo":null},{"id":"794975600628953088","text":"RT @nytimes: 12 of our most memorable photographs from the 2016 U.S. presidential campaign https://t.co/o9kPkwNh73","year":2016,"date":"2016-11-05","favorites":0,"retweets":0,"replyTo":null},{"id":"794926958941507584","text":"if you wanna know where i'm at, i'm moderately enjoying a dunkin donuts latte","year":2016,"date":"2016-11-05","favorites":1,"retweets":0,"replyTo":null},{"id":"794925663421612032","text":"what day is it even is it election day","year":2016,"date":"2016-11-05","favorites":0,"retweets":0,"replyTo":null},{"id":"794925523902365697","text":"THIS. FUCKING. RULES. https://t.co/onTDwDeOKd","year":2016,"date":"2016-11-05","favorites":0,"retweets":0,"replyTo":null},{"id":"794925342611881984","text":"This is podcasts jumping the shark right https://t.co/9SuORIIbnQ","year":2016,"date":"2016-11-05","favorites":0,"retweets":0,"replyTo":null},{"id":"794909602022309889","text":"@AlleeManning a hahahahah","year":2016,"date":"2016-11-05","favorites":0,"retweets":0,"replyTo":"2ls_2es"},{"id":"794906856141586432","text":"@replyall @priyom_org @BBCWorld &lt;3","year":2016,"date":"2016-11-05","favorites":0,"retweets":0,"replyTo":"replyall"},{"id":"794903167930662913","text":"Election 2016: Cyber War\n\n(the sequel no one wanted to the original no one liked, in true American fashion)","year":2016,"date":"2016-11-05","favorites":0,"retweets":0,"replyTo":null},{"id":"794902326423285761","text":"@AlleeManning hello I'd like to commission \"A Purchase Kid At Duke\" for my zine plz","year":2016,"date":"2016-11-05","favorites":1,"retweets":0,"replyTo":"2ls_2es"},{"id":"794803990508748800","text":"@priyom_org hello @replyall can you yes yes no this for me","year":2016,"date":"2016-11-05","favorites":0,"retweets":0,"replyTo":"priyom_org"},{"id":"794782221341196289","text":"RT @awinston: Oh we all love journalism until it comes time to pay for it https://t.co/TvrGSVQg7Z","year":2016,"date":"2016-11-05","favorites":0,"retweets":0,"replyTo":null},{"id":"794743726342045696","text":"Really excited for the sleep party","year":2016,"date":"2016-11-05","favorites":1,"retweets":0,"replyTo":null},{"id":"794741771825778688","text":"RT @brianstelter: Obama said it, but Clinton could say it too https://t.co/Lh03Jf0OQM","year":2016,"date":"2016-11-05","favorites":0,"retweets":0,"replyTo":null},{"id":"662365556008460289","text":"@Operation_KKK stop trolling","year":2015,"date":"2015-11-05","favorites":1,"retweets":0,"replyTo":"Operation_KKK"},{"id":"662355850514837504","text":"@Anon4Good whats the hold up?","year":2015,"date":"2015-11-05","favorites":0,"retweets":0,"replyTo":"Anon4Good"},{"id":"662348491029651456","text":"#OpKKK’s great ability to drum up press coverage and apparent inability to actually produce anything is not going to help their cause","year":2015,"date":"2015-11-05","favorites":1,"retweets":1,"replyTo":null},{"id":"662326773737259008","text":"@flowingdata For statics? Haven’t been able to pass on excess work for 3+ years now, everyone onto D3, etc - datavis-jobs google list best","year":2015,"date":"2015-11-05","favorites":1,"retweets":0,"replyTo":"flowingdata"},{"id":"662326497496178688","text":"Starting my new internet-hacker-themed podcast morning show, Fawkes and Friends","year":2015,"date":"2015-11-05","favorites":3,"retweets":2,"replyTo":null},{"id":"662289598689734657","text":"RT @Matan_gilat: Holy shit, I'm on /r/dataisbeautiful 's front page! https://t.co/cDSzVj7rGW","year":2015,"date":"2015-11-05","favorites":0,"retweets":0,"replyTo":null},{"id":"662286319511576577","text":"RT @RAIDERS: .@NFLFilms joined us for Raiders-Jets last weekend.\n\nThey captured some incredible moments: https://t.co/qabty6HtDH https://t.…","year":2015,"date":"2015-11-05","favorites":0,"retweets":0,"replyTo":null},{"id":"662285137850343424","text":"holy shit Ben Carson just dropped some fire\n\nhttps://t.co/CIXBRmHZAn","year":2015,"date":"2015-11-05","favorites":0,"retweets":0,"replyTo":null},{"id":"662109192728272896","text":"i rail against pie charts for like a year straight and let one slip by and it gets retweeted by Hillary Clinton how am I gonna explain this","year":2015,"date":"2015-11-05","favorites":5,"retweets":0,"replyTo":null},{"id":"662109078387228672","text":"guys its a pizza pie chart how can you not love that https://t.co/Oum0kcqSOx","year":2015,"date":"2015-11-05","favorites":1,"retweets":0,"replyTo":null},{"id":"662108307084193792","text":"RT @origiful: Probably the most unfortunate dot dot dot in any political retweet, ever: https://t.co/PVZY7GUEoU","year":2015,"date":"2015-11-05","favorites":0,"retweets":0,"replyTo":null},{"id":"662104330892386304","text":"RT @HillaryClinton: Guilty as charged. 🍕 https://t.co/qnKHHsAUE2","year":2015,"date":"2015-11-05","favorites":0,"retweets":0,"replyTo":null},{"id":"662057239201607680","text":"RT @splcenter: Racial Slurs Are Woven Deep Into The American Landscape https://t.co/oXMHwwFbCC by @vocativ https://t.co/ayuS6RKN5O","year":2015,"date":"2015-11-05","favorites":0,"retweets":0,"replyTo":null},{"id":"530065606675271681","text":"@marg1nal Something about 'Forceful Presence' http://t.co/WatrDSq12k","year":2014,"date":"2014-11-05","favorites":1,"retweets":0,"replyTo":"marg1nal"},{"id":"530027016821567489","text":"RT @ddprrt: \"What's bower?\"\n\"A package manager, install it with npm.\"\n\"What's npm?\"\n\"A package manager, you can install it with brew\"\n\"What…","year":2014,"date":"2014-11-05","favorites":0,"retweets":0,"replyTo":null},{"id":"530010607685496832","text":"@andymangold I legitimately like it, but maybe it’s because I am a millennial (not part of that project btw)","year":2014,"date":"2014-11-05","favorites":0,"retweets":0,"replyTo":"andymangold"},{"id":"530008885760114689","text":"@andymangold http://t.co/0mtmfplCLk","year":2014,"date":"2014-11-05","favorites":0,"retweets":0,"replyTo":"andymangold"},{"id":"530007737024126976","text":"RT @DLeonhardt: The most detailed - and beautiful - maps of last night's vote, showing precinct-by-precinct results, http://t.co/n3TSPkxUhE","year":2014,"date":"2014-11-05","favorites":0,"retweets":0,"replyTo":null},{"id":"530006960876564481","text":"RT @CapobiaNB: Why run for office and join this system that clearly doesn't work - another reason millennials shrug at the vote &amp; balk at r…","year":2014,"date":"2014-11-05","favorites":0,"retweets":0,"replyTo":null},{"id":"530006766437011457","text":"Oakland….\n\n….\n\n….\n\nSchaff? Really? Reaaaaallllly?","year":2014,"date":"2014-11-05","favorites":0,"retweets":0,"replyTo":null},{"id":"530006602234204160","text":"RT @KTVU: Libby Schaaf claims victory in #Oakland mayor's race. After 15 rds of ranked choice voting Schaaf claims 62.8% of votes Kaplan 2n…","year":2014,"date":"2014-11-05","favorites":0,"retweets":0,"replyTo":null},{"id":"529978626994106368","text":"RT @Stimpdawg: There's Now An App That Analyzes Your Personality And Compares It To Your Facebook Friends http://t.co/4hlWgqcOl5 #apps #per…","year":2014,"date":"2014-11-05","favorites":0,"retweets":0,"replyTo":null},{"id":"529817231136661504","text":"RT @nytgraphics: How different groups voted: http://t.co/CdnPf5wV9p http://t.co/7MuIjEB1Yc","year":2014,"date":"2014-11-05","favorites":0,"retweets":0,"replyTo":null},{"id":"529815739155644418","text":"RT @nprviz: Hey, @CNN! We’ve found a way to fit a little more data onto a building. #justsayin #nprparty http://t.co/Z82raMzy3R http://t.co…","year":2014,"date":"2014-11-05","favorites":0,"retweets":0,"replyTo":null},{"id":"397807045736689664","text":"Photo: nevver: Tools of Criminal Mischief http://t.co/88oSQ2u7yE","year":2013,"date":"2013-11-05","favorites":0,"retweets":0,"replyTo":null},{"id":"265590793983627265","text":"RT @newsycombinator: Ratchet: Prototyping iPhone apps in simple HTML, CSS, and JS http://t.co/rnd7TsoD","year":2012,"date":"2012-11-05","favorites":0,"retweets":0,"replyTo":null},{"id":"265586794773487616","text":"RT @YourAnonNews: Remember, remember the 5th of November. The Gunpowder Treason and Plot. I see no reason, why the Gunpowder Treason sho ...","year":2012,"date":"2012-11-05","favorites":0,"retweets":0,"replyTo":null},{"id":"265582702445613056","text":"http://t.co/gnhXhCen","year":2012,"date":"2012-11-05","favorites":0,"retweets":0,"replyTo":null},{"id":"265580716891451392","text":"RT @dansinker: brilliant. RT @kirstenpowers10: KEEP CALM AND TRUST NATE SILVER http://t.co/LFzIJCr2","year":2012,"date":"2012-11-05","favorites":0,"retweets":0,"replyTo":null},{"id":"265580365169713154","text":"Watching V for Vendetta with the girlfriend. Remember, remember...","year":2012,"date":"2012-11-05","favorites":0,"retweets":0,"replyTo":null},{"id":"265578507390812161","text":"RT @jeffjarvis: 2/2 RT @JimmyTraina: If extra charge shows up on your bill next month, you must call and they will waive extra chargers.","year":2012,"date":"2012-11-05","favorites":0,"retweets":0,"replyTo":null},{"id":"265578469554012160","text":"RT @jeffjarvis: Hope so RT @JimmyTraina: FYI, Verizon rep told me they will NOT charge people affected by storm if they go over data/tex ...","year":2012,"date":"2012-11-05","favorites":0,"retweets":0,"replyTo":null},{"id":"265573978951802882","text":"@alyssa011968 No one can ask you to delete your pictures, and anyone who does certainly deserves their picture taken. Stay strong.","year":2012,"date":"2012-11-05","favorites":1,"retweets":0,"replyTo":"Betulapendula22"},{"id":"265561632585965568","text":"RT @AnonymouSkY: Big Ben strikes 9 for about 9000 present Anons atm #anonymous #OpVendetta #Nov5 http://t.co/wC17g1tR","year":2012,"date":"2012-11-05","favorites":0,"retweets":0,"replyTo":null},{"id":"265541498253234176","text":"I love how, now, NYTimes has not only the best journalists of my generation (Nate Silver, etc) but programmers @mbostock @jashkenas","year":2012,"date":"2012-11-05","favorites":0,"retweets":0,"replyTo":null},{"id":"265540997738545152","text":"RT @KevinQ: Head just came close to exploding witnessing @mbostock and @jashkenas discuss data. Yikes!","year":2012,"date":"2012-11-05","favorites":0,"retweets":0,"replyTo":null},{"id":"265515798267842561","text":"RT @bryanconnor: This is the visualization I'll have in front of me on election night: http://t.co/MoeLCwAw (on @thewhyaxis)","year":2012,"date":"2012-11-05","favorites":0,"retweets":0,"replyTo":null},{"id":"265507763709423616","text":"RT @mibi: There is certainly a Dunbar number for the number of apps and monthly services a person can actively use.  For me its &lt; 20.","year":2012,"date":"2012-11-05","favorites":0,"retweets":0,"replyTo":null},{"id":"132942317853216768","text":"Just lol'd at @enjalot's comments in this code for a project I'm working on in D3… http://t.co/dT1ugKcf","year":2011,"date":"2011-11-05","favorites":0,"retweets":0,"replyTo":null},{"id":"5463350369","text":"playing a little Call of Duty 4: Modern Warfare. http://raptr.com/pseudoplacebo","year":2009,"date":"2009-11-05","favorites":0,"retweets":0,"replyTo":null},{"id":"5462522795","text":"Okay listening to old Faithless really makes me think- I've wanted Merriweather esque dancey abstract electronica since I've &lt;3'd music.","year":2009,"date":"2009-11-05","favorites":0,"retweets":0,"replyTo":null},{"id":"992329246","text":"Trying to motivate myself to walk into these shops and ask for job apps. \"Oh,\" I say \"the money you'll make\"","year":2008,"date":"2008-11-05","favorites":0,"retweets":0,"replyTo":null},{"id":"991830602","text":"It's almost too good to be true. My fingers are crossed for the secret service.","year":2008,"date":"2008-11-05","favorites":0,"retweets":0,"replyTo":null},{"id":"991800874","text":"I was so happy last night I forgot to tweet. Incredible.","year":2008,"date":"2008-11-05","favorites":0,"retweets":0,"replyTo":null},{"id":"390475012","text":"Back home. Skipped class for the last period of the day, went to a spanish class I'm not supposed to be in. Had incredible luck with sub.","year":2007,"date":"2007-11-05","favorites":0,"retweets":0,"replyTo":null},{"id":"389505732","text":"My face just froze off.","year":2007,"date":"2007-11-05","favorites":0,"retweets":0,"replyTo":null},{"id":"389488482","text":"Awake, with the sun for the first time. I am pretty tired. I will listen to radiohead and zone out. Yesss...","year":2007,"date":"2007-11-05","favorites":0,"retweets":0,"replyTo":null},{"id":"389120912","text":"Plan: Go to sleep. Wake up. Shower. Dress. Eat. Clean. School. Eat. Clean / Sleep.","year":2007,"date":"2007-11-05","favorites":0,"retweets":0,"replyTo":null},{"id":"388879202","text":"Gonna clean a bit and then passss outtttt.","year":2007,"date":"2007-11-05","favorites":0,"retweets":0,"replyTo":null},{"id":"388764272","text":"In a fucking amazing mood. Amazing. Amazing. So good. 14/10. Hopefully it'll rollover into my week.","year":2007,"date":"2007-11-05","favorites":0,"retweets":0,"replyTo":null},{"id":"388663822","text":"Back from Max's. 300 was pretty amazing. I am tired. At least I get Tuesday off.","year":2007,"date":"2007-11-05","favorites":0,"retweets":0,"replyTo":null}],"posts":[{"slug":"robots/someday/ejfox-news","title":"ejfox.news Phase 1: Core Development Plan","year":2024,"date":"2024-11-05T17:00:28.000Z","dek":null,"type":"post","tags":["development","projects","tools"]}],"scrobbles":[{"date":"2023-11-05","year":2023,"count":39,"topTracks":["MF DOOM - Eucalyptus","Tobe Nwigwe - FATHER FIGURE","Everlast - What It's Like","JAY-Z - Brooklyn's Finest","Ben Snow - Out in the Streets - Voltage Remix"],"topArtists":["MF DOOM","Tobe Nwigwe","Everlast"]},{"date":"2021-11-05","year":2021,"count":31,"topTracks":["Mick Jenkins - Gucci Tried to Tell Me","monte booker - Kolors","Saba - Photosynthesis","DUCKWRTH - Birthday Suit","BLAck pARty - DANCING"],"topArtists":["Mick Jenkins","monte booker","Saba"]},{"date":"2020-11-05","year":2020,"count":22,"topTracks":["311 - All Mixed Up","311 - Amber","311 - Beautiful Disaster","311 - Good Feeling","311 - Down"],"topArtists":["311","Death Cab for Cutie","Broken Social Scene"]},{"date":"2019-11-05","year":2019,"count":6,"topTracks":["JPEGMAFIA - Free The Frail","JPEGMAFIA - Post Verified Lifestyle","JPEGMAFIA - BasicBitchTearGas","JPEGMAFIA - DOTS FREESTYLE REMIX","JPEGMAFIA - BUTTERMILK JESUS TYPE BEAT"],"topArtists":["JPEGMAFIA"]},{"date":"2018-11-05","year":2018,"count":101,"topTracks":["Hiatus Kaiyote - Laputa","Hiatus Kaiyote - Creations Part One","Hiatus Kaiyote - Borderline With My Atoms","Hiatus Kaiyote - Breathing Underwater","Hiatus Kaiyote - Cicada"],"topArtists":["Hiatus Kaiyote","Danny Brown","Nao"]},{"date":"2016-11-05","year":2016,"count":22,"topTracks":["James Blake - Radio Silence","James Blake - Points","James Blake - Love Me in Whatever Way","James Blake - Timeless","James Blake - f.o.r.e.v.e.r."],"topArtists":["James Blake"]},{"date":"2013-11-05","year":2013,"count":2,"topTracks":["Danny Brown - Smokin & Drinkin","Bonobo - Heaven for the Sinner"],"topArtists":["Danny Brown","Bonobo"]},{"date":"2010-11-05","year":2010,"count":45,"topTracks":["Animal Collective - Chocolate Girl","Animal Collective - Everyone Whistling","Animal Collective - La Rapet","Animal Collective - Bat You'll Fly","Animal Collective - Someday I'll Grow to Be As Tall As the Giant"],"topArtists":["Animal Collective","David Sedaris","J.K. Rowling"]},{"date":"2007-11-05","year":2007,"count":121,"topTracks":["Aidan Hawken - Neighborhood","Bat for Lashes - What's a Girl to Do?","Bat for Lashes - Sad Eyes","Bat for Lashes - Bat's Mouth","Bat for Lashes - Horse and I"],"topArtists":["Aidan Hawken","Bat for Lashes","Boys Like Girls"]},{"date":"2006-11-05","year":2006,"count":106,"topTracks":["Nine Inch Nails - Every Day Is Exactly the Same","Nine Inch Nails - With Teeth","Nine Inch Nails - Only","Nine Inch Nails - Getting Smaller","Nine Inch Nails - Sunspots"],"topArtists":["Nine Inch Nails","Nirvana","No Doubt"]}],"commits":[{"sha":"7df5d42","message":"feat(theme): complete migration to vulpes-reddishnovember","year":2025,"date":"2025-11-06T04:12:18Z","repo":"dotfiles"},{"sha":"91ccc5e","message":"feat: track lazygit and zsh configs in dotfiles","year":2025,"date":"2025-11-06T04:12:04Z","repo":"dotfiles"},{"sha":"fc57087","message":"chore: clean up unused method","year":2021,"date":"2021-11-05T16:23:10Z","repo":"website"},{"sha":"bcb5354","message":"chore: update package.json","year":2021,"date":"2021-11-05T16:12:52Z","repo":"website"},{"sha":"0f53158","message":"style(logo): change logo in header","year":2021,"date":"2021-11-05T16:12:35Z","repo":"website"},{"sha":"b3fccc9","message":"feat(router): add scrollToTop to home page","year":2021,"date":"2021-11-05T16:12:19Z","repo":"website"}]}