{
  "content": "<p class=\"mb-4\">Vector embeddings for Criterion films enabling searches like \"films about existentialism\" for cinephiles who want deep thematic connections</p>",
  "html": "<p class=\"mb-4\">Vector embeddings for Criterion films enabling searches like \"films about existentialism\" for cinephiles who want deep thematic connections</p>",
  "title": "criterion-embedding-viz",
  "metadata": {
    "words": 21,
    "images": 0,
    "links": 0,
    "codeBlocks": 0,
    "headers": {
      "h1": 1
    },
    "toc": [
      {
        "text": "criterion-embedding-viz",
        "slug": "criterion-embedding-viz",
        "level": "h1",
        "children": []
      }
    ],
    "type": "post",
    "sourcePath": "../../../../../code/website2/content/blog/projects/criterion-embedding-viz.md",
    "sourceDir": "/Users/ejfox/Library/Mobile Documents/iCloud~md~obsidian/Documents/ejfox/"
  }
}